matrix_rssbot/__init__.py
matrix_rssbot/__main__.py
matrix_rssbot/classes/__init__.py
matrix_rssbot/classes/bot.py
matrix_rssbot/classes/logging.py
matrix_rssbot/classes/callbacks/__init__.py
matrix_rssbot/classes/callbacks/invite.py
matrix_rssbot/classes/callbacks/message.py
matrix_rssbot/classes/callbacks/roommember.py
matrix_rssbot/classes/callbacks/sync.py
matrix_rssbot/classes/commands/__init__.py
matrix_rssbot/classes/commands/addfeed.py
matrix_rssbot/classes/commands/botinfo.py
matrix_rssbot/classes/commands/eventtype.py
matrix_rssbot/classes/commands/help.py
matrix_rssbot/classes/commands/listfeeds.py
matrix_rssbot/classes/commands/privacy.py
matrix_rssbot/classes/commands/processfeeds.py
matrix_rssbot/classes/commands/removefeed.py
matrix_rssbot/classes/commands/unknown.py
matrix_rssbot-0.1.9.dist-info/METADATA
matrix_rssbot-0.1.9.dist-info/WHEEL
matrix_rssbot-0.1.9.dist-info/entry_points.txt
matrix_rssbot-0.1.9.dist-info/licenses/LICENSE
matrix_rssbot-0.1.9.dist-info/RECORD
