Metadata-Version: 2.3
Name: matrix-rssbot
Version: 0.1.9
Summary: Simple RSS feed bridge for Matrix
Project-URL: Homepage, https://git.private.coffee/PrivateCoffee/matrix-rssbot
Project-URL: Bug Tracker, https://git.private.coffee/PrivateCoffee/matrix-rssbot/issues
Author-email: "Private.coffee Team" <support@private.coffee>
License: Copyright (c) 2024 Private.coffee Team <support@private.coffee>
License-File: LICENSE
Classifier: License :: OSI Approved :: MIT License
Classifier: Operating System :: OS Independent
Classifier: Programming Language :: Python :: 3
Requires-Python: >=3.10
Requires-Dist: feedparser
Requires-Dist: future>=1.0.0
Requires-Dist: markdown2
Requires-Dist: matrix-nio>=0.24.0
Requires-Dist: setuptools
